dashing/__init__.py
dashing/dashing.py
py_dashing-0.3.dev0.dist-info/LICENSE
py_dashing-0.3.dev0.dist-info/METADATA
py_dashing-0.3.dev0.dist-info/WHEEL
py_dashing-0.3.dev0.dist-info/top_level.txt
py_dashing-0.3.dev0.dist-info/RECORD
