Metadata-Version: 2.1
Name: py-dashing
Version: 0.3.dev0
Summary: High-level terminal-based dashboard - Forked from FedericoCeratto/dashing
Home-page: https://github.com/hemanthmalla/dashing
Author: Federico Ceratto
Author-email: federico@debian.org
License: LGPL
Keywords: dashboard terminal
Platform: UNKNOWN
Classifier: Development Status :: 3 - Alpha
Classifier: Environment :: Console
Classifier: Intended Audience :: Developers
Classifier: License :: OSI Approved :: GNU Lesser General Public License v3 (LGPLv3)
Requires-Dist: blessed
